{"version":"3.10.1","examples":[{"id":"./spec/models/author_spec.rb[1:1]","description":"can be created with valid data","full_description":"Author can be created with valid data","status":"passed","file_path":"./spec/models/author_spec.rb","line_number":4,"run_time":0.012888807,"pending_message":null},{"id":"./spec/models/author_spec.rb[1:2:1]","description":"is expected to validate that :name cannot be empty/falsy","full_description":"Author Basic validations is expected to validate that :name cannot be empty/falsy","status":"passed","file_path":"./spec/models/author_spec.rb","line_number":10,"run_time":0.017183747,"pending_message":null},{"id":"./spec/models/author_spec.rb[1:2:2]","description":"is expected to validate that :name is case-sensitively unique","full_description":"Author Basic validations is expected to validate that :name is case-sensitively unique","status":"passed","file_path":"./spec/models/author_spec.rb","line_number":11,"run_time":0.015251755,"pending_message":null},{"id":"./spec/models/author_spec.rb[1:2:3]","description":"is expected to validate that the length of :phone_number is 10","full_description":"Author Basic validations is expected to validate that the length of :phone_number is 10","status":"passed","file_path":"./spec/models/author_spec.rb","line_number":12,"run_time":0.013702712,"pending_message":null},{"id":"./spec/models/post_spec.rb[1:1]","description":"can be created with valid data","full_description":"Post can be created with valid data","status":"passed","file_path":"./spec/models/post_spec.rb","line_number":5,"run_time":0.019806975,"pending_message":null},{"id":"./spec/models/post_spec.rb[1:2:1]","description":"is expected to validate that :title cannot be empty/falsy","full_description":"Post Basic validations is expected to validate that :title cannot be empty/falsy","status":"passed","file_path":"./spec/models/post_spec.rb","line_number":16,"run_time":0.016982063,"pending_message":null},{"id":"./spec/models/post_spec.rb[1:2:2]","description":"is expected to validate that the length of :content is at least 250","full_description":"Post Basic validations is expected to validate that the length of :content is at least 250","status":"passed","file_path":"./spec/models/post_spec.rb","line_number":17,"run_time":0.00939308,"pending_message":null},{"id":"./spec/models/post_spec.rb[1:2:3]","description":"is expected to validate that the length of :summary is at most 250","full_description":"Post Basic validations is expected to validate that the length of :summary is at most 250","status":"passed","file_path":"./spec/models/post_spec.rb","line_number":18,"run_time":0.008432354,"pending_message":null},{"id":"./spec/models/post_spec.rb[1:2:4]","description":"is expected to validate that :category is either ‹\"Fiction\"› or ‹\"Non-Fiction\"›","full_description":"Post Basic validations is expected to validate that :category is either ‹\"Fiction\"› or ‹\"Non-Fiction\"›","status":"passed","file_path":"./spec/models/post_spec.rb","line_number":19,"run_time":0.013217588,"pending_message":null},{"id":"./spec/models/post_spec.rb[1:3:1]","description":"is expected to allow :title to be ‹\"You Won't Believe These True Facts\"›","full_description":"Post Custom validations: title is clickbait is expected to allow :title to be ‹\"You Won't Believe These True Facts\"›","status":"passed","file_path":"./spec/models/post_spec.rb","line_number":23,"run_time":0.005868648,"pending_message":null},{"id":"./spec/models/post_spec.rb[1:3:2]","description":"is expected not to allow :title to be ‹\"True Facts\"›","full_description":"Post Custom validations: title is clickbait is expected not to allow :title to be ‹\"True Facts\"›","status":"passed","file_path":"./spec/models/post_spec.rb","line_number":24,"run_time":0.004348205,"pending_message":null}],"summary":{"duration":0.145710761,"example_count":11,"failure_count":0,"pending_count":0,"errors_outside_of_examples_count":0},"summary_line":"11 examples, 0 failures"}